blastoise/__init__.py
blastoise/fs/__init__.py
blastoise/fs/exception.py
blastoise/fs/hierarchy.py
blastoise/fs/local_file_system.py
blastoise/parquet/__init__.py
blastoise/parquet/exception.py
blastoise/parquet/loader.py
blastoise/util/__init__.py
blastoise/util/path.py
blastoise-0.0.1.dist-info/LICENSE
blastoise-0.0.1.dist-info/METADATA
blastoise-0.0.1.dist-info/WHEEL
blastoise-0.0.1.dist-info/top_level.txt
blastoise-0.0.1.dist-info/zip-safe
blastoise-0.0.1.dist-info/RECORD
